Metadata-Version: 2.1
Name: yves-distribution-gaussian-binomial
Version: 1.4
Summary: Gaussian and Binomial distributions
Author: YVES PANFULE GOUE
Author-email: goueyvespanfule@gmail.com
